webullsdkquotescore/__init__.py
webullsdkquotescore/default_retry_policy.py
webullsdkquotescore/exceptions.py
webullsdkquotescore/quotes_client.py
webullsdkquotescore/quotes_decoder.py
webullsdkquotescore/quotes_payload_decoder.py
webullsdkquotescore/quotes_topic.py
webullsdkquotescore/grpc/__init__.py
webullsdkquotescore/grpc/connect.py
webullsdkquotescore/grpc/connect_status.py
webullsdkquotescore/grpc/core.py
webullsdkquotescore/grpc/error.py
webullsdkquotescore/grpc/grpc_client.py
webullsdkquotescore/grpc/grpc_retry_policy.py
webullsdkquotescore/grpc/grpc_signature_composer.py
webullsdkquotescore/grpc/msg.py
webullsdkquotescore/grpc/retry.py
webullsdkquotescore/grpc/pb/__init__.py
webullsdkquotescore/grpc/pb/gateway_pb2.py
webullsdkquotescore/grpc/pb/gateway_pb2_grpc.py
webullsdkquotescore/grpc/proto/__init__.py
webullsdkquotescore/grpc/task/__init__.py
webullsdkquotescore/grpc/task/task_timer.py
webull_python_sdk_quotes_core-0.1.18.dist-info/METADATA
webull_python_sdk_quotes_core-0.1.18.dist-info/WHEEL
webull_python_sdk_quotes_core-0.1.18.dist-info/top_level.txt
webull_python_sdk_quotes_core-0.1.18.dist-info/RECORD
