Metadata-Version: 2.4
Name: webull-python-sdk-quotes-core
Version: 0.1.18
Summary: The quotes core module of Webull Python SDK.
Home-page: 
Author: Webull
Author-email: 
License: Apache License 2.0
Platform: any
Requires-Dist: paho-mqtt==1.6.1
Requires-Dist: grpcio==1.51.1
Requires-Dist: grpcio-tools==1.51.1
Requires-Dist: protobuf==4.21.12
Requires-Dist: webull-python-sdk-core==0.1.18
Dynamic: author
Dynamic: description-content-type
Dynamic: license
Dynamic: platform
Dynamic: requires-dist
Dynamic: summary
